kitsiso/__init__.py
kitsiso/_notification.py
kitsiso/_notifier.py
kitsiso-0.2.0.dist-info/LICENSE.txt
kitsiso-0.2.0.dist-info/METADATA
kitsiso-0.2.0.dist-info/WHEEL
kitsiso-0.2.0.dist-info/top_level.txt
kitsiso-0.2.0.dist-info/RECORD
