Metadata-Version: 2.1
Name: kitsiso
Version: 0.2.0
Summary: Library for sending desktop notifications.
Home-page: https://andreas19.github.io/kitsiso/
Author: Andreas Suhre
Author-email: andreas19@posteo.eu
License: BSD-3-Clause
Project-URL: Source code, https://github.com/andreas19/kitsiso/
Platform: UNKNOWN
Classifier: Development Status :: 4 - Beta
Classifier: Intended Audience :: Developers
Classifier: License :: OSI Approved :: BSD License
Classifier: Natural Language :: English
Classifier: Operating System :: POSIX :: Linux
Classifier: Programming Language :: Python :: 3
Classifier: Programming Language :: Python :: 3.7
Classifier: Topic :: Desktop Environment
Classifier: Topic :: Software Development :: Libraries
Requires-Python: >=3.7
Requires-Dist: dcar (>=0.1.0)
